{
    "workflowId": "8a8a1064-cf41-4733-9447-6895986b7b37",
    "nodes": [
        {
            "node_id": "2f7ce3da-1851-4c8d-a6b3-cb7f9ab33c93",
            "type": "db_connector",
            "inputs": [],
            "outputs": [],
            "fields": {
                "databaseType": "PostgreSQL",
                "url": "jdbc:postgresql://localhost:5432/Quizlet",
                "username": "postgres",
                "password": "ibnrasalfakih12141522",
                "driver": "org.postgresql.Driver"
            }
        },
        {
            "node_id": "5c5d0ec5-d7e0-4045-9e22-eec55794e9b6",
            "type": "db_table_creator",
            "inputs": ["2f7ce3da-1851-4c8d-a6b3-cb7f9ab33c93"],
            "outputs": [],
            "fields": {
                "tableName": " my second TABLE",
                "columns": [
                    {
                    "columnName": "id",
                    "columnType": "SERIAL PRIMARY KEY"
                    },
                    {
                    "columnName": "username",
                    "columnType": "VARCHAR(255) NOT NULL"
                    },
                    {
                    "columnName": "created_at",
                    "columnType": "TIMESTAMP DEFAULT CURRENT_TIMESTAMP"
                    }
                ]
            }
        }
	]
}